dp_path_util/__init__.py
dp_path_util/repo_locator.py
dp_path_util-1.0.0.dist-info/LICENSE
dp_path_util-1.0.0.dist-info/METADATA
dp_path_util-1.0.0.dist-info/WHEEL
dp_path_util-1.0.0.dist-info/top_level.txt
dp_path_util-1.0.0.dist-info/RECORD
